s2mosaic/__init__.py
s2mosaic/__version__.py
s2mosaic/coordinator.py
s2mosaic/data_reader.py
s2mosaic/frequent_coverage.py
s2mosaic/helpers.py
s2mosaic/masking.py
s2mosaic/mosaic_core.py
s2mosaic/mosaic_utils.py
s2mosaic/sentinel_2_index.gpkg
s2mosaic/stac_utils.py
s2mosaic-1.1.0.dist-info/licenses/LICENSE
s2mosaic-1.1.0.dist-info/METADATA
s2mosaic-1.1.0.dist-info/WHEEL
s2mosaic-1.1.0.dist-info/top_level.txt
s2mosaic-1.1.0.dist-info/RECORD
