Metadata-Version: 2.4
Name: s2mosaic
Version: 1.1.0
Summary: Python library for making cloud-free Sentinel-2 mosaics
Author-email: Nick Wright <nicholas.wright@dpird.wa.gov.au>
License-Expression: MIT
Project-URL: Homepage, https://github.com/DPIRD-DMA/S2Mosaic
Keywords: sentinel-2,satellite,mosaic,remote-sensing
Requires-Python: >=3.10
License-File: LICENSE
Requires-Dist: geopandas>=1.0.3
Requires-Dist: numbagg>=0.9.0
Requires-Dist: omnicloudmask>=1.7.0
Requires-Dist: planetary-computer>=1.0.0
Requires-Dist: pystac-client>=0.8.6
Requires-Dist: scipy>=1.10
Dynamic: license-file
